{
	"coords": { "right_ascension": {"hours": 18, "minutes": 18, "seconds": 48}, "declination": {"degrees": -13, "minutes": 49, "seconds": 0}, "distance": {"ly": 5700} },
	"axis_rotation": { "x_axis": 0, "y_axis": 0, "z_axis": 0 },
	"texture_layers":
	[
		{
			"texture": "stellarview:textures/environment/halo_template.png",
			"rgba": {"red": 255, "green": 0, "blue": 0, "alpha": 255},
			"blend": true,
			"size": 4488626469,
			"min_size": 0.9,
			"clamp_at_min_size": true,
			"rotation": 0,
			"uv": { "flip_uv": false }
		},
		{
			"texture": "stellarview:textures/environment/nebula/eagle_nebula.png",
			"rgba": {"red": 255, "green": 255, "blue": 255, "alpha": 255},
			"blend": true,
			"size": 4488626469,
			"min_size": 0.5,
			"clamp_at_min_size": true,
			"rotation": 0,
			"uv": { "flip_uv": false }
		}
	]
}